multasker/__init__.py
multasker/log/Logger.py
multasker/log/__init__.py
multasker/process/StarMapThreadPool.py
multasker/process/ThreadPoolExecutor.py
multasker/process/TwoQueue.py
multasker/process/__init__.py
multasker/test/Test.py
multasker/test/__init__.py
multasker/util/Singleton.py
multasker/util/__init__.py
multasker-0.3.3.dist-info/licenses/LICENSE
test/FileHasher.py
test/TestLogger.py
test/TestStarMapThreadPool.py
test/TestThreadPoolExecutor.py
test/TestTwoQueue.py
test/__init__.py
multasker-0.3.3.dist-info/METADATA
multasker-0.3.3.dist-info/WHEEL
multasker-0.3.3.dist-info/top_level.txt
multasker-0.3.3.dist-info/RECORD
