Metadata-Version: 2.4
Name: multasker
Version: 0.3.3
Summary: A package for managing multiprocessing and multithreading tasks
Home-page: https://pypi.org/project/multasker/
Author: kalanik0a
Author-email: seanjklum@gmail.com
Project-URL: Source, https://github.com/kalanik0a/multasker
Classifier: Programming Language :: Python :: 3
Classifier: License :: OSI Approved :: MIT License
Classifier: Operating System :: OS Independent
Requires-Python: >=3.6
License-File: LICENSE
Dynamic: author
Dynamic: author-email
Dynamic: classifier
Dynamic: description
Dynamic: description-content-type
Dynamic: home-page
Dynamic: license-file
Dynamic: project-url
Dynamic: requires-python
Dynamic: summary
